[
  {
    "listing": "/assignments.html",
    "items": [
      "/assignments/hw00-setup.html",
      "/assignments/ws01-functions.html",
      "/assignments/hw01-simulation.html",
      "/assignments/ws02-estimation.html"
    ]
  },
  {
    "listing": "/complete_notes.html",
    "items": [
      "/complete_notes/cn01-intro_simulation_complete.html",
      "/complete_notes/cn02-intro_sampling_complete.html",
      "/complete_notes/cn03-statistical_foundations_complete.html",
      "/complete_notes/cn04-SRS_complete.html"
    ]
  },
  {
    "listing": "/notes.html",
    "items": [
      "/notes/cn00-welcome.html",
      "/notes/cn01-intro_simulation.html",
      "/notes/cn02-intro_sampling.html",
      "/notes/cn03-statistical_foundations.html"
    ]
  },
  {
    "listing": "/weekly_details.html",
    "items": [
      "/weekly_details/wk01.html",
      "/weekly_details/wk02.html",
      "/weekly_details/wk03.html"
    ]
  }
]